All_File/Notes/Decoder/Decoder2.v
module decoder2(y,a,en);
input [1:0]a;
input en;
output [3:0]y;
wire [1:0]w;
not not1(w[0],a[0]);
not not2(w[1],a[1]);
and and1(y[0],w[0],w[1],en);
and and2(y[1],a[0],w[1],en);
and and3(y[2],w[0],a[1],en);
and and4(y[3],a[0],a[1],en);
endmodule

All_File/Notes/Decoder/Decoder3.v
`include"decoder2.v"

module decoder3(y,a,en);
input [2:0]a;
input en;
output [7:0]y;
wire [2:0]w;
not not1(w[0],a[2]);
and and1(w[1],w[0],en);
and and2(w[2],a[2],en);
decoder2 a1(y[3:0],a[1:0],w[1]);
decoder2 a2(y[7:4],a[1:0],w[2]);
endmodule

All_File/Notes/Decoder/Test3.v
module test;
reg [2:0]a;
reg en;
wire [7:0]y;
decoder3 a1(y,a,en);

initial begin
$dumpfile("decoder3.vcd");
$dumpvars(0,test);
en=1'b0;a=3'bxxx;
#5 en=1'b1;a=3'b000;
#5 en=1'b1;a=3'b001;
#5 en=1'b1;a=3'b010;
#5 en=1'b1;a=3'b011;
#5 en=1'b1;a=3'b100;
#5 en=1'b1;a=3'b101;
#5 en=1'b1;a=3'b110;
#5 en=1'b1;a=3'b111;
#5 $finish;
end

initial begin
$monitor("Time=%d,en=%b a=%b y=%b ",$time,en,a,y);
end

endmodule

All_File/Notes/Decoder/decoder3.vcd
$date
	Tue Jun 14 11:36:24 2022
$end
$version
	Icarus Verilog
$end
$timescale
	1s
$end
$scope module test $end
$var wire 8 ! y [7:0] $end
$var reg 3 " a [2:0] $end
$var reg 1 # en $end
$scope module a1 $end
$var wire 3 $ a [2:0] $end
$var wire 1 # en $end
$var wire 8 % y [7:0] $end
$var wire 3 & w [2:0] $end
$scope module a1 $end
$var wire 2 ' a [1:0] $end
$var wire 1 ( en $end
$var wire 4 ) y [3:0] $end
$var wire 2 * w [1:0] $end
$upscope $end
$scope module a2 $end
$var wire 2 + a [1:0] $end
$var wire 1 , en $end
$var wire 4 - y [3:0] $end
$var wire 2 . w [1:0] $end
$upscope $end
$upscope $end
$upscope $end
$enddefinitions $end
#0
$dumpvars
bx .
b0 -
0,
bx +
bx *
b0 )
0(
bx '
b0x &
b0 %
bx $
0#
bx "
b0 !
$end
#5
b11 *
b11 .
b1 )
b1 !
b1 %
b0 -
1(
0,
b0 '
b0 +
b11 &
b0 "
b0 $
1#
#10
b10 *
b10 !
b10 %
b10 )
b10 .
b1 '
b1 +
b1 "
b1 $
#15
b1 *
b100 !
b100 %
b100 )
b1 .
b10 '
b10 +
b10 "
b10 $
#20
b0 *
b1000 !
b1000 %
b1000 )
b0 .
b11 '
b11 +
b11 "
b11 $
#25
0(
b1 -
1,
b11 *
b10000 !
b10000 %
b0 )
b11 .
b100 &
b0 '
b0 +
b100 "
b100 $
#30
b10 *
b10 .
b100000 !
b100000 %
b10 -
b1 '
b1 +
b101 "
b101 $
#35
b1 *
b1 .
b1000000 !
b1000000 %
b100 -
b10 '
b10 +
b110 "
b110 $
#40
b0 *
b0 .
b10000000 !
b10000000 %
b1000 -
b11 '
b11 +
b111 "
b111 $
