All_File/Notes/Decoder/Decoder2.v
module decoder2(y,a,en);
input [1:0]a;
input en;
output [3:0]y;
wire [1:0]w;
not not1(w[0],a[0]);
not not2(w[1],a[1]);
and and1(y[0],w[0],w[1],en);
and and2(y[1],a[0],w[1],en);
and and3(y[2],w[0],a[1],en);
and and4(y[3],a[0],a[1],en);
endmodule

All_File/Notes/Decoder/Decoder3.v
`include"decoder2.v"

module decoder3(y,a,en);
input [2:0]a;
input en;
output [7:0]y;
wire [2:0]w;
not not1(w[0],a[2]);
and and1(w[1],w[0],en);
and and2(w[2],a[2],en);
decoder2 a1(y[3:0],a[1:0],w[1]);
decoder2 a2(y[7:4],a[1:0],w[2]);
endmodule

All_File/Notes/Decoder/Decoder4.v
`include"decoder3.v"

module decoder4(y,a,en);
input [3:0]a;
input en;
output [15:0]y;
wire [2:0]w;
not not1(w[0],a[3]);
and and1(w[1],w[0],en);
and and2(w[2],a[3],en);
decoder3 a1(y[7:0],a[2:0],w[1]);
decoder3 a2(y[15:8],a[2:0],a[3]);
endmodule

All_File/Notes/Decoder/Test4.v
module test;
reg [3:0]a;
reg en;
wire [15:0]y;
decoder4 a1(y,a,en);

initial begin
$dumpfile("decoder4.vcd");
$dumpvars(0,test);
en=1'b0;a=4'bxxxx;
#5 en=1'b1;a=4'b0000;
#5 en=1'b1;a=4'b0001;
#5 en=1'b1;a=4'b0010;
#5 en=1'b1;a=4'b0011;
#5 en=1'b1;a=4'b0100;
#5 en=1'b1;a=4'b0101;
#5 en=1'b1;a=4'b0110;
#5 en=1'b1;a=4'b0111;
#5 en=1'b1;a=4'b1000;
#5 en=1'b1;a=4'b1001;
#5 en=1'b1;a=4'b1010;
#5 en=1'b1;a=4'b1011;
#5 en=1'b1;a=4'b1100;
#5 en=1'b1;a=4'b1101;
#5 en=1'b1;a=4'b1110;
#5 en=1'b1;a=4'b1111;
#5 $finish;
end

initial begin
$monitor("Time=%d,en=%b a=%b y=%b ",$time,en,a,y);
end

endmodule

All_File/Notes/Decoder/decoder4.vcd
$date
	Tue Jun 14 11:38:05 2022
$end
$version
	Icarus Verilog
$end
$timescale
	1s
$end
$scope module test $end
$var wire 16 ! y [15:0] $end
$var reg 4 " a [3:0] $end
$var reg 1 # en $end
$scope module a1 $end
$var wire 4 $ a [3:0] $end
$var wire 1 # en $end
$var wire 16 % y [15:0] $end
$var wire 3 & w [2:0] $end
$scope module a1 $end
$var wire 3 ' a [2:0] $end
$var wire 1 ( en $end
$var wire 8 ) y [7:0] $end
$var wire 3 * w [2:0] $end
$scope module a1 $end
$var wire 2 + a [1:0] $end
$var wire 1 , en $end
$var wire 4 - y [3:0] $end
$var wire 2 . w [1:0] $end
$upscope $end
$scope module a2 $end
$var wire 2 / a [1:0] $end
$var wire 1 0 en $end
$var wire 4 1 y [3:0] $end
$var wire 2 2 w [1:0] $end
$upscope $end
$upscope $end
$scope module a2 $end
$var wire 3 3 a [2:0] $end
$var wire 1 4 en $end
$var wire 8 5 y [7:0] $end
$var wire 3 6 w [2:0] $end
$scope module a1 $end
$var wire 2 7 a [1:0] $end
$var wire 1 8 en $end
$var wire 4 9 y [3:0] $end
$var wire 2 : w [1:0] $end
$upscope $end
$scope module a2 $end
$var wire 2 ; a [1:0] $end
$var wire 1 < en $end
$var wire 4 = y [3:0] $end
$var wire 2 > w [1:0] $end
$upscope $end
$upscope $end
$upscope $end
$upscope $end
$enddefinitions $end
#0
$dumpvars
bx >
bx =
x<
bx ;
bx :
bx 9
x8
bx 7
bx 6
bx 5
x4
bx 3
bx 2
b0 1
00
bx /
bx .
b0 -
0,
bx +
b0x *
b0 )
0(
bx '
b0x &
bx00000000 %
bx $
0#
bx "
bx00000000 !
$end
#5
b1 )
b1 -
b11 .
b11 2
b11 :
b11 >
b0 9
b1 !
b1 %
b0 5
b0 =
1,
08
0<
b11 *
b0 +
b0 /
b0 7
b0 ;
b1 6
1(
b0 '
b0 3
04
b11 &
b0 "
b0 $
1#
#10
b10 .
b10 !
b10 %
b10 )
b10 -
b10 2
b10 :
b10 >
b1 +
b1 /
b1 7
b1 ;
b1 '
b1 3
b1 "
b1 $
#15
b1 .
b100 !
b100 %
b100 )
b100 -
b1 2
b1 :
b1 >
b10 +
b10 /
b10 7
b10 ;
b10 '
b10 3
b10 "
b10 $
#20
b0 .
b1000 !
b1000 %
b1000 )
b1000 -
b0 2
b0 :
b0 >
b11 +
b11 /
b11 7
b11 ;
b11 '
b11 3
b11 "
b11 $
#25
0,
b1 1
10
b11 .
b10000 !
b10000 %
b10000 )
b0 -
b11 2
b11 :
b11 >
b100 *
b0 6
b0 +
b0 /
b0 7
b0 ;
b100 '
b100 3
b100 "
b100 $
#30
b10 .
b10 2
b100000 !
b100000 %
b100000 )
b10 1
b10 :
b10 >
b1 +
b1 /
b1 7
b1 ;
b101 '
b101 3
b101 "
b101 $
#35
b1 .
b1 2
b1000000 !
b1000000 %
b1000000 )
b100 1
b1 :
b1 >
b10 +
b10 /
b10 7
b10 ;
b110 '
b110 3
b110 "
b110 $
#40
b0 .
b0 2
b10000000 !
b10000000 %
b10000000 )
b1000 1
b0 :
b0 >
b11 +
b11 /
b11 7
b11 ;
b111 '
b111 3
b111 "
b111 $
#45
b0 -
b1 5
b1 9
0,
18
0(
00
b11 .
b11 2
b100000000 !
b100000000 %
b0 )
b0 1
b11 :
b11 >
b1 *
0<
b100 &
b0 +
b0 /
b0 7
b0 ;
b11 6
b0 '
b0 3
14
b1000 "
b1000 $
#50
b10 .
b10 2
b10 :
b1000000000 !
b1000000000 %
b10 5
b10 9
b10 >
b1 +
b1 /
b1 7
b1 ;
b1 '
b1 3
b1001 "
b1001 $
#55
b1 .
b1 2
b1 :
b10000000000 !
b10000000000 %
b100 5
b100 9
b1 >
b10 +
b10 /
b10 7
b10 ;
b10 '
b10 3
b1010 "
b1010 $
#60
b0 .
b0 2
b0 :
b100000000000 !
b100000000000 %
b1000 5
b1000 9
b0 >
b11 +
b11 /
b11 7
b11 ;
b11 '
b11 3
b1011 "
b1011 $
#65
08
b1 =
b11 .
b11 2
1<
b11 :
b1000000000000 !
b1000000000000 %
b10000 5
b0 9
b11 >
b0 *
b100 6
b0 +
b0 /
b0 7
b0 ;
b100 '
b100 3
b1100 "
b1100 $
#70
b10 .
b10 2
b10 :
b10 >
b10000000000000 !
b10000000000000 %
b100000 5
b10 =
b1 +
b1 /
b1 7
b1 ;
b101 '
b101 3
b1101 "
b1101 $
#75
b1 .
b1 2
b1 :
b1 >
b100000000000000 !
b100000000000000 %
b1000000 5
b100 =
b10 +
b10 /
b10 7
b10 ;
b110 '
b110 3
b1110 "
b1110 $
#80
b0 .
b0 2
b0 :
b0 >
b1000000000000000 !
b1000000000000000 %
b10000000 5
b1000 =
b11 +
b11 /
b11 7
b11 ;
b111 '
b111 3
b1111 "
b1111 $
